README.rst
setup.py
classipy.egg-info/PKG-INFO
classipy.egg-info/SOURCES.txt
classipy.egg-info/dependency_links.txt
classipy.egg-info/entry_points.txt
classipy.egg-info/requires.txt
classipy.egg-info/top_level.txt
classy/__init__.py
classy/classifiers.py
classy/data.py
classy/etbase.py
classy/evaluate.py
classy/extract.py
classy/generate.py
classy/helpers.py
classy/learn.py
classy/predict.py
classy/select.py
classy/test_extract.py
classy/test_transform.py
classy/transform.py