Metadata-Version: 1.1
Name: classipy
Version: 1.0.0
Summary: a command-line based text classification tool
Home-page: https://github.com/fnl/classipy
Author: Florian Leitner
Author-email: florian.leitner@gmail.com
License: AGPLv3
Keywords: text classification machine learning information retrieval
Platform: UNKNOWN
Classifier: Development Status :: 3 - Alpha
Classifier: License :: OSI Approved :: GNU Affero General Public License v3
Classifier: Programming Language :: Python :: 3
Classifier: Programming Language :: Python :: 3.3
Classifier: Programming Language :: Python :: 3.4
Classifier: Topic :: Scientific/Engineering :: Information Analysis
Classifier: Topic :: Software Development :: Libraries
Classifier: Topic :: Text Processing
Classifier: Topic :: Text Processing :: Linguistic
